circuit_breaker/__init__.py
circuit_breaker/circuit_breaker.py
circuit_breaker/enums.py
circuit_breaker/exceptions.py
circuit_breaker/middleware.py
circuit_breaker/schemas.py
circuit_breaker_fastapi-0.1.0.dist-info/METADATA
circuit_breaker_fastapi-0.1.0.dist-info/WHEEL
circuit_breaker_fastapi-0.1.0.dist-info/top_level.txt
circuit_breaker_fastapi-0.1.0.dist-info/RECORD
