Metadata-Version: 2.2
Name: circuit_breaker_fastapi
Version: 0.1.0
Summary: Circuit breaker pattern implementation fastapi
Home-page: https://github.com/fmelihh/circuit-breaker-pattern-fastapi
Author: Furkan Melih Ercan
Author-email: Furkan Melih ERCAN <furkanmelihercan.98@gmail.com>
License: MIT
Requires-Python: >=3.11.8
Requires-Dist: fastapi
Requires-Dist: pendulum
Dynamic: author
Dynamic: home-page
Dynamic: requires-python
